actspotter/__init__.py
actspotter/model/keras_metadata.pb
actspotter/model/meta.json
actspotter/model/saved_model.pb
actspotter/model/variables/variables.data-00000-of-00001
actspotter/model/variables/variables.index
actspotter-0.1.3.dist-info/LICENSE
actspotter-0.1.3.dist-info/METADATA
actspotter-0.1.3.dist-info/WHEEL
actspotter-0.1.3.dist-info/top_level.txt
actspotter-0.1.3.dist-info/RECORD
